Metadata-Version: 2.1
Name: gae-impersonate-credentials
Version: 0.1.5
Summary: Get an GCP Credentials instance
Home-page: https://github.com/pirika-inc/gae-impersonate-credentials
Author: Pirika, Inc.
Author-email: info+python-package@pirika.org
License: UNKNOWN
Platform: UNKNOWN
Requires-Python: >=3.7
License-File: LICENSE
